pymeten/__init__.py
pymeten/itutils.py
pymeten/triton_benchmark.py
pymeten-0.0.5.dist-info/METADATA
pymeten-0.0.5.dist-info/WHEEL
pymeten-0.0.5.dist-info/top_level.txt
pymeten-0.0.5.dist-info/RECORD
